{
  "name": "Brúarfoss - Iceland's Bluest Waterfall",
  "description": "Brúarfoss, translating to \"Bridge Falls,\" has earned the nickname \"Iceland's Bluest Waterfall\" for its strikingly vivid, almost electric blue water that seems impossibly bright even by Icelandic standards. This relatively small but extraordinarily beautiful cascade is located in southwest Iceland between Þingvellir National Park and the Geysir geothermal area, making it an ideal addition to a Golden Circle itinerary for travelers willing to make a short detour from the main route. The waterfall's remarkable blue color originates from glacial meltwater flowing from Langjökull glacier, which travels down through the Hvítá river system before branching into the Brúará river and tumbling over a series of rocky steps to create Brúarfoss. The glacial sediment suspended in the water—fine particles ground to powder by the glacier's movement—scatters light in a way that produces this characteristic intense blue hue, a phenomenon enhanced by Iceland's often overcast skies which provide diffused lighting that makes colors appear even more saturated. Unlike Iceland's massive cascading waterfalls, Brúarfoss is relatively modest in scale, dropping only about 7-10 meters across multiple tiers and channels, but what it lacks in height it more than compensates for in visual impact and photographic appeal. The water splits into several distinct channels that weave between dark volcanic rocks, creating a complex braided pattern of bright blue streams, small cascades, and churning pools before reuniting downstream. For many years, Brúarfoss was a hidden gem known primarily to locals and adventurous photographers who were willing to undertake a 7-kilometer (4.4-mile) hike across private farmland to reach it, but the waterfall's popularity exploded through social media sharing, leading to overcrowding and access issues. In response, authorities constructed an official parking area and access trail in 2023, dramatically improving the situation—visitors can now park legally (for 750 ISK / approximately $5 USD) and reach the waterfall via an easy 5-minute walk on a maintained path. This improved access has made Brúarfoss one of Iceland's most visitor-friendly hidden gems, accessible to travelers of all fitness levels without sacrificing its natural beauty. The short trail from the parking area follows the Brúará river upstream, passing smaller cascades and pools that provide preview glimpses of the blue water before arriving at the main waterfall. The viewing area allows visitors to approach remarkably close to the rushing water, and while there are no formal barriers, caution is advised as rocks can be slippery. The area around Brúarfoss also features other scenic spots along the river including upstream cascades and downstream pools where the brilliant blue water continues its journey through the lava landscape.",
  "address": "Brúará River, 801 Selfoss, Iceland",
  "coordinates": {
    "longitude": -20.5167,
    "latitude": 64.2639,
    "altitude": 80.0
  },
  "rating": 4.7,
  "reviews_count": 3450,
  "category": "Waterfall",
  "website": "https://www.south.is/en/bruarfoss",
  "phone": null,
  "images": [
    "https://www.south.is/images/bruarfoss-blue-water.jpg"
  ],
  "opening_hours": {
    "access": "Year-round (easier in summer)",
    "parking": "Official parking area (750 ISK / $5 USD)",
    "walk_duration": "5 minutes from parking to waterfall",
    "admission": "Parking fee only",
    "distance_from_reykjavik": "90 km (56 miles), 1.5 hours drive",
    "distance_from_geysir": "15 km (12 minutes drive)",
    "height": "7-10 meters across multiple tiers",
    "best_time": "Summer for easier access and longer daylight"
  }
}
