{
  "name": "Stykkishólmur - Snæfellsnes Gateway & Ferry Port",
  "description": "Stykkishólmur establishes Snæfellsnes Peninsula's largest town commercial hub where approximately 1,200 residents inhabit picturesque harbor setting dramatic basalt island formations Breiðafjörður Bay creating postcard-perfect Icelandic fishing village aesthetics supporting tourism economy ferry operations Baldur vessel connecting Snæfellsnes Vestfir ðir Westfjords enabling vehicle passenger transport across Breiðafjörður shortcutting lengthy Ring Road detours saving travelers hours establishing strategic transportation node regional significance exceeding population size suggesting raw functional importance. Baldur ferry operates Breiðafjörður daily summer schedules connecting Stykkishólmur Brjánslækur Westfjords enabling Snæfellsnes-Westfjords circuit itineraries without backtracking Route 1 creating efficient travel routing particularly beneficial visitors maximizing limited timeframes exploring western Iceland regions though winter schedules reduce frequency requiring careful itinerary planning consulting current timetables ensuring transportation availability matching travel dates. Norwegian Church Norska Húsið represents 1832 timber structure Norwegian prefabricated kit house establishing oldest two-story wooden building Iceland preserving architectural heritage while functioning museum cultural venue hosting exhibitions concerts maintaining historical building adaptive reuse demonstrating successful heritage preservation economic development cultural programming creating multipurpose community assets beyond pure museum functions. Library Volcano Museum Eldfjallasafn provides comprehensive volcanic education exhibits explaining Iceland's geological volcanic processes earthquake activity eruption history demonstrating educational tourism infrastructure small town punching above weight class offering sophisticated scientific presentations accessible general audiences establishing Stykkishólmur educational destination beyond purely scenic harbor attractions supporting diverse tourism interests geological education family-friendly activities. Sugandisey Island basalt formation connected causeway harbor supports historic lighthouse providing walking path summit panoramic town harbor views establishing accessible viewpoint requiring minimal hiking effort rewarding visitors comprehensive photographic perspectives encompassing colorful buildings harbor activities Breiðafjörður islands distant mountains creating exceptional compositions particularly sunrise sunset golden hour lighting conditions favoring landscape photography enthusiasts seeking iconic Icelandic harbor imagery. Fishing industry continues economic importance though tourism increasingly supplements traditional maritime livelihoods where harbor accommodates commercial fishing vessels tour boats ferry operations creating busy working waterfront authentic maritime atmosphere contrasting purely tourist-oriented harbors lacking functional commercial fishing maintaining genuine character working community beyond tourism facade establishing appealing qualities visitors seeking authentic Iceland experiences beyond manufactured tourist attractions. Breiðafjörður Bay islands thousands small rocky formations creating complex archipelago supporting seabird populations rich marine ecosystems where ferry crossings enable wildlife viewing opportunities spotting puffins eagles seals whales establishing bonus nature experiences beyond purely transportation functions though wildlife sightings depend seasonal timing weather conditions luck requiring realistic expectations avoiding guaranteed wildlife promises unrealistic tourism marketing. Accommodation dining options support overnight visitors though limited capacity high season requires advance bookings avoiding disappointment finding rooms restaurants fully booked particularly summer months when Snæfellsnes popularity peaks straining small town infrastructure creating seasonal capacity challenges typical popular Icelandic destinations experiencing concentrated tourism seasons overwhelming local service provision capabilities.",
  "address": "Stykkishólmur, 340 Snæfellsnes Peninsula",
  "coordinates": {
    "longitude": -22.7333,
    "latitude": 65.0667,
    "altitude": 5.0
  },
  "rating": 4.5,
  "reviews_count": 5620,
  "category": "Town - West Iceland",
  "website": "https://www.stykkisholmur.is",
  "phone": "+354 433 8120",
  "images": [
    "https://www.west.is/images/stykkisholmur-harbor.jpg"
  ],
  "opening_hours": {
    "population": "~1,200",
    "location": "Snæfellsnes Peninsula, Breiðafjörður Bay",
    "baldur_ferry": "Daily summer to Brjánslækur (Westfjords)",
    "norwegian_church": "Norska Húsið 1832, museum/cultural venue",
    "volcano_museum": "Library of Water & Eldfjallasafn",
    "sugandisey": "Island lighthouse, causeway access, harbor views",
    "character": "Picturesque harbor, ferry port, fishing, tourism"
  }
}